LICENSE
MANIFEST.in
README.md
package.json
setup.py
sankey/Sankey.py
sankey/__init__.py
sankey/_imports_.py
sankey/metadata.json
sankey/package-info.json
sankey/sankey.min.js
sankey/sankey.min.js.map
sankey.egg-info/PKG-INFO
sankey.egg-info/SOURCES.txt
sankey.egg-info/dependency_links.txt
sankey.egg-info/top_level.txt