Metadata-Version: 1.0
Name: sankey
Version: 0.0.1
Summary: Simple Sankey arrow diagram for Dash
Home-page: UNKNOWN
Author: Pascal Corpet <pascal@corpet.net>
Author-email: UNKNOWN
License: MIT
Platform: UNKNOWN
